<?xml version="1.0" encoding="UTF-8"?>

<samplemap ID="TROMBONE 2" RRGroupAmount="1" MicPositions=";" SaveMode="2">
  <sample Root="46" LoKey="46" HiKey="46" LoVel="0" HiVel="50" RRGroup="1"
          FileName="{PROJECT_FOLDER}OldTrombone/Sustain/Trombone_Sustain_A#1_v1_1.wav"
          Duplicate="0" Normalized="1" NormalizedPeak="29.9019" SampleStartMod="50000"
          LoopEnabled="1" LoopEnd="221015" LoopStart="100000" LoopXFade="15000"
          UpperVelocityXFade="40" Volume="3" MonolithOffset="0" MonolithLength="303104"
          SampleRate="44100"/>
  <sample Root="46" LoKey="46" HiKey="46" LoVel="11" HiVel="92" RRGroup="1"
          FileName="{PROJECT_FOLDER}OldTrombone/Sustain/Trombone_Sustain_A#1_v3_1.wav"
          Duplicate="0" Normalized="1" NormalizedPeak="9.52048" SampleStartMod="50000"
          LoopEnabled="1" LoopEnd="288203" LoopStart="100000" LoopXFade="15000"
          LowerVelocityXFade="40" UpperVelocityXFade="40" Volume="3" MonolithOffset="303104"
          MonolithLength="376832" SampleRate="44100"/>
  <sample Root="46" LoKey="46" HiKey="46" LoVel="53" HiVel="125" RRGroup="1"
          FileName="{PROJECT_FOLDER}OldTrombone/Sustain/Trombone_Sustain_A#1_v4_1.wav"
          Duplicate="0" Normalized="1" NormalizedPeak="2.51914" SampleStartMod="50000"
          LoopEnabled="1" LoopEnd="121264" LoopStart="60735" LoopXFade="15000"
          LowerVelocityXFade="40" UpperVelocityXFade="32" Volume="3" MonolithOffset="679936"
          MonolithLength="163840" SampleRate="44100"/>
  <sample Root="46" LoKey="46" HiKey="46" LoVel="94" HiVel="127" RRGroup="1"
          FileName="{PROJECT_FOLDER}OldTrombone/Sustain/Trombone_Sustain_A#1_v5_1.wav"
          Duplicate="0" Normalized="1" NormalizedPeak="1.24068" SampleStartMod="50000"
          LoopEnabled="1" LoopEnd="154819" LoopStart="67312" LoopXFade="15000"
          LowerVelocityXFade="32" Volume="3" MonolithOffset="843776" MonolithLength="258048"
          SampleRate="44100"/>
  <sample Root="58" LoKey="58" HiKey="58" LoVel="0" HiVel="92" RRGroup="1"
          FileName="{PROJECT_FOLDER}OldTrombone/Sustain/Trombone_Sustain_A#2_v3_1.wav"
          Duplicate="0" Normalized="1" NormalizedPeak="9.64661" SampleStartMod="50000"
          LoopEnabled="1" LoopEnd="319877" LoopStart="100000" LoopXFade="15000"
          LowerVelocityXFade="0" UpperVelocityXFade="40" Volume="3" MonolithOffset="1101824"
          MonolithLength="421888" SampleRate="44100"/>
  <sample Root="58" LoKey="58" HiKey="58" LoVel="53" HiVel="107" RRGroup="1"
          FileName="{PROJECT_FOLDER}OldTrombone/Sustain/Trombone_Sustain_A#2_v4_1.wav"
          Duplicate="0" Normalized="1" NormalizedPeak="2.59497" SampleStartMod="50000"
          LoopEnabled="1" LoopEnd="158773" LoopStart="73014" LoopXFade="15000"
          LowerVelocityXFade="40" UpperVelocityXFade="13" Volume="3" MonolithOffset="1523712"
          MonolithLength="212992" SampleRate="44100"/>
  <sample Root="58" LoKey="58" HiKey="58" LoVel="86" HiVel="127" RRGroup="1"
          FileName="{PROJECT_FOLDER}OldTrombone/Sustain/Trombone_Sustain_A#2_v5_1.wav"
          Duplicate="0" Normalized="1" NormalizedPeak="1.25577" SampleStartMod="50000"
          LoopEnabled="1" LoopEnd="99280" LoopStart="44574" LoopXFade="15000"
          LowerVelocityXFade="20" Volume="3" MonolithOffset="1736704" MonolithLength="163840"
          SampleRate="44100"/>
  <sample Root="45" LoKey="44" HiKey="45" LoVel="0" HiVel="50" RRGroup="1"
          FileName="{PROJECT_FOLDER}OldTrombone/Sustain/Trombone_Sustain_A1_v1_1.wav"
          Duplicate="0" Normalized="1" NormalizedPeak="15.8192" SampleStartMod="50000"
          LoopEnabled="1" LoopEnd="246685" LoopStart="100000" LoopXFade="15000"
          UpperVelocityXFade="40" Volume="3" MonolithOffset="1900544" MonolithLength="327680"
          SampleRate="44100"/>
  <sample Root="45" LoKey="44" HiKey="45" LoVel="11" HiVel="92" RRGroup="1"
          FileName="{PROJECT_FOLDER}OldTrombone/Sustain/Trombone_Sustain_A1_v3_1.wav"
          Duplicate="0" Normalized="1" NormalizedPeak="11.9385" SampleStartMod="50000"
          LoopEnabled="1" LoopEnd="283150" LoopStart="100000" LoopXFade="15000"
          LowerVelocityXFade="40" UpperVelocityXFade="40" Volume="3" MonolithOffset="2228224"
          MonolithLength="380928" SampleRate="44100"/>
  <sample Root="45" LoKey="44" HiKey="45" LoVel="53" HiVel="125" RRGroup="1"
          FileName="{PROJECT_FOLDER}OldTrombone/Sustain/Trombone_Sustain_A1_v4_1.wav"
          Duplicate="0" Normalized="1" NormalizedPeak="2.74875" SampleStartMod="50000"
          LoopEnabled="1" LoopEnd="178176" LoopStart="100000" LoopXFade="15000"
          LowerVelocityXFade="40" UpperVelocityXFade="32" Volume="3" MonolithOffset="2609152"
          MonolithLength="180224" SampleRate="44100"/>
  <sample Root="45" LoKey="44" HiKey="45" LoVel="94" HiVel="127" RRGroup="1"
          FileName="{PROJECT_FOLDER}OldTrombone/Sustain/Trombone_Sustain_A1_v5_1.wav"
          Duplicate="0" Normalized="1" NormalizedPeak="2.90371" SampleStartMod="50000"
          LoopEnabled="1" LoopEnd="110023" LoopStart="63445" LoopXFade="15000"
          LowerVelocityXFade="32" Volume="3" MonolithOffset="2789376" MonolithLength="155648"
          SampleRate="44100"/>
  <sample Root="57" LoKey="56" HiKey="57" LoVel="0" HiVel="92" RRGroup="1"
          FileName="{PROJECT_FOLDER}OldTrombone/Sustain/Trombone_Sustain_A2_v3_1.wav"
          Duplicate="0" Normalized="1" NormalizedPeak="11.4693" SampleStartMod="50000"
          LoopEnabled="1" LoopEnd="237624" LoopStart="100000" LoopXFade="15000"
          LowerVelocityXFade="0" UpperVelocityXFade="40" Volume="3" MonolithOffset="2945024"
          MonolithLength="376832" SampleRate="44100"/>
  <sample Root="57" LoKey="56" HiKey="57" LoVel="53" HiVel="125" RRGroup="1"
          FileName="{PROJECT_FOLDER}OldTrombone/Sustain/Trombone_Sustain_A2_v4_1.wav"
          Duplicate="0" Normalized="1" NormalizedPeak="2.54144" SampleStartMod="50000"
          LoopEnabled="1" LoopEnd="148384" LoopStart="69592" LoopXFade="15000"
          LowerVelocityXFade="40" UpperVelocityXFade="32" Volume="3" MonolithOffset="3321856"
          MonolithLength="188416" SampleRate="44100"/>
  <sample Root="57" LoKey="56" HiKey="57" LoVel="94" HiVel="127" RRGroup="1"
          FileName="{PROJECT_FOLDER}OldTrombone/Sustain/Trombone_Sustain_A2_v5_1.wav"
          Duplicate="0" Normalized="1" NormalizedPeak="1.40761" SampleStartMod="50000"
          LoopEnabled="1" LoopEnd="108060" LoopStart="57310" LoopXFade="15000"
          LowerVelocityXFade="32" Volume="3" MonolithOffset="3510272" MonolithLength="155648"
          SampleRate="44100"/>
  <sample Root="48" LoKey="47" HiKey="48" LoVel="0" HiVel="50" RRGroup="1"
          FileName="{PROJECT_FOLDER}OldTrombone/Sustain/Trombone_Sustain_C2_v1_1.wav"
          Duplicate="0" Normalized="1" NormalizedPeak="26.8856" SampleStartMod="50000"
          LoopEnabled="1" LoopEnd="254497" LoopStart="100000" LoopXFade="15000"
          UpperVelocityXFade="40" Volume="3" MonolithOffset="3665920" MonolithLength="327680"
          SampleRate="44100"/>
  <sample Root="48" LoKey="47" HiKey="48" LoVel="11" HiVel="92" RRGroup="1"
          FileName="{PROJECT_FOLDER}OldTrombone/Sustain/Trombone_Sustain_C2_v3_1.wav"
          Duplicate="0" Normalized="1" NormalizedPeak="8.77127" SampleStartMod="50000"
          LoopEnabled="1" LoopEnd="370167" LoopStart="100000" LoopXFade="15000"
          LowerVelocityXFade="40" UpperVelocityXFade="40" Volume="3" MonolithOffset="3993600"
          MonolithLength="475136" SampleRate="44100"/>
  <sample Root="48" LoKey="47" HiKey="48" LoVel="53" HiVel="125" RRGroup="1"
          FileName="{PROJECT_FOLDER}OldTrombone/Sustain/Trombone_Sustain_C2_v4_1.wav"
          Duplicate="0" Normalized="1" NormalizedPeak="2.8204" SampleStartMod="50000"
          LoopEnabled="1" LoopEnd="150126" LoopStart="79817" LoopXFade="15000"
          LowerVelocityXFade="40" UpperVelocityXFade="32" Volume="3" MonolithOffset="4468736"
          MonolithLength="200704" SampleRate="44100"/>
  <sample Root="48" LoKey="47" HiKey="48" LoVel="94" HiVel="127" RRGroup="1"
          FileName="{PROJECT_FOLDER}OldTrombone/Sustain/Trombone_Sustain_C2_v5_1.wav"
          Duplicate="0" Normalized="1" NormalizedPeak="2.25504" SampleStartMod="50000"
          LoopEnabled="1" LoopEnd="142857" LoopStart="82852" LoopXFade="15000"
          LowerVelocityXFade="32" Volume="3" MonolithOffset="4669440" MonolithLength="184320"
          SampleRate="44100"/>
  <sample Root="60" LoKey="59" HiKey="60" LoVel="0" HiVel="80" RRGroup="1"
          FileName="{PROJECT_FOLDER}OldTrombone/Sustain/Trombone_Sustain_C3_v1_1.wav"
          Duplicate="0" Normalized="1" NormalizedPeak="16.1562" SampleStartMod="50000"
          LoopEnabled="1" LoopEnd="301300" LoopStart="100000" LoopXFade="15000"
          UpperVelocityXFade="40" Volume="3" MonolithOffset="4853760" MonolithLength="372736"
          SampleRate="44100"/>
  <sample Root="60" LoKey="59" HiKey="60" LoVel="43" HiVel="125" RRGroup="1"
          FileName="{PROJECT_FOLDER}OldTrombone/Sustain/Trombone_Sustain_C3_v4_1.wav"
          Duplicate="0" Normalized="1" NormalizedPeak="2.79994" SampleStartMod="50000"
          LoopEnabled="1" LoopEnd="151016" LoopStart="94207" LoopXFade="15000"
          LowerVelocityXFade="40" UpperVelocityXFade="32" Volume="3" MonolithOffset="5226496"
          MonolithLength="188416" SampleRate="44100"/>
  <sample Root="60" LoKey="59" HiKey="60" LoVel="94" HiVel="127" RRGroup="1"
          FileName="{PROJECT_FOLDER}OldTrombone/Sustain/Trombone_Sustain_C3_v5_1.wav"
          Duplicate="0" Normalized="1" NormalizedPeak="1.47143" SampleStartMod="50000"
          LoopEnabled="1" LoopEnd="142766" LoopStart="78092" LoopXFade="15000"
          LowerVelocityXFade="32" Volume="6" MonolithOffset="5414912" MonolithLength="176128"
          SampleRate="44100"/>
  <sample Root="51" LoKey="51" HiKey="51" LoVel="0" HiVel="50" RRGroup="1"
          FileName="{PROJECT_FOLDER}OldTrombone/Sustain/Trombone_Sustain_D#2_v1_1.wav"
          Duplicate="0" Normalized="1" NormalizedPeak="21.4599" SampleStartMod="50000"
          LoopEnabled="1" LoopEnd="225376" LoopStart="100000" LoopXFade="15000"
          UpperVelocityXFade="40" Volume="3" MonolithOffset="5591040" MonolithLength="299008"
          SampleRate="44100"/>
  <sample Root="51" LoKey="51" HiKey="51" LoVel="11" HiVel="92" RRGroup="1"
          FileName="{PROJECT_FOLDER}OldTrombone/Sustain/Trombone_Sustain_D#2_v3_1.wav"
          Duplicate="0" Normalized="1" NormalizedPeak="13.3825" SampleStartMod="50000"
          LoopEnabled="1" LoopEnd="312371" LoopStart="100000" LoopXFade="15000"
          LowerVelocityXFade="40" UpperVelocityXFade="40" Volume="3" MonolithOffset="5890048"
          MonolithLength="389120" SampleRate="44100"/>
  <sample Root="51" LoKey="51" HiKey="51" LoVel="53" HiVel="125" RRGroup="1"
          FileName="{PROJECT_FOLDER}OldTrombone/Sustain/Trombone_Sustain_D#2_v4_1.wav"
          Duplicate="0" Normalized="1" NormalizedPeak="2.11091" SampleStartMod="50000"
          LoopEnabled="1" LoopEnd="140742" LoopStart="78880" LoopXFade="15000"
          LowerVelocityXFade="40" UpperVelocityXFade="32" Volume="3" MonolithOffset="6279168"
          MonolithLength="184320" SampleRate="44100"/>
  <sample Root="51" LoKey="51" HiKey="51" LoVel="94" HiVel="127" RRGroup="1"
          FileName="{PROJECT_FOLDER}OldTrombone/Sustain/Trombone_Sustain_D#2_v5_1.wav"
          Duplicate="0" Normalized="1" NormalizedPeak="1.39429" SampleStartMod="50000"
          LoopEnabled="1" LoopEnd="151236" LoopStart="100000" LoopXFade="15000"
          LowerVelocityXFade="32" Volume="3" MonolithOffset="6463488" MonolithLength="196608"
          SampleRate="44100"/>
  <sample Root="63" LoKey="63" HiKey="63" LoVel="0" HiVel="50" RRGroup="1"
          FileName="{PROJECT_FOLDER}OldTrombone/Sustain/Trombone_Sustain_D#3_v1_1.wav"
          Duplicate="0" Normalized="1" NormalizedPeak="17.1456" SampleStartMod="50000"
          LoopEnabled="1" LoopEnd="249214" LoopStart="100000" LoopXFade="15000"
          UpperVelocityXFade="40" Volume="3" MonolithOffset="6660096" MonolithLength="323584"
          SampleRate="44100"/>
  <sample Root="63" LoKey="63" HiKey="63" LoVel="11" HiVel="92" RRGroup="1"
          FileName="{PROJECT_FOLDER}OldTrombone/Sustain/Trombone_Sustain_D#3_v3_1.wav"
          Duplicate="0" Normalized="1" NormalizedPeak="12.7574" SampleStartMod="50000"
          LoopEnabled="1" LoopEnd="333520" LoopStart="100000" LoopXFade="15000"
          LowerVelocityXFade="40" UpperVelocityXFade="40" Volume="3" MonolithOffset="6983680"
          MonolithLength="458752" SampleRate="44100"/>
  <sample Root="63" LoKey="63" HiKey="63" LoVel="53" HiVel="125" RRGroup="1"
          FileName="{PROJECT_FOLDER}OldTrombone/Sustain/Trombone_Sustain_D#3_v4_1.wav"
          Duplicate="0" Normalized="1" NormalizedPeak="3.91781" SampleStartMod="50000"
          LoopEnabled="1" LoopEnd="197981" LoopStart="100000" LoopXFade="15000"
          LowerVelocityXFade="40" UpperVelocityXFade="32" Volume="3" MonolithOffset="7442432"
          MonolithLength="245760" SampleRate="44100"/>
  <sample Root="63" LoKey="63" HiKey="63" LoVel="94" HiVel="127" RRGroup="1"
          FileName="{PROJECT_FOLDER}OldTrombone/Sustain/Trombone_Sustain_D#3_v5_1.wav"
          Duplicate="0" Normalized="1" NormalizedPeak="1.96959" SampleStartMod="50000"
          LoopEnabled="1" LoopEnd="115401" LoopStart="66223" LoopXFade="15000"
          LowerVelocityXFade="32" Volume="3" MonolithOffset="7688192" MonolithLength="159744"
          SampleRate="44100"/>
  <sample Root="50" LoKey="49" HiKey="50" LoVel="0" HiVel="50" RRGroup="1"
          FileName="{PROJECT_FOLDER}OldTrombone/Sustain/Trombone_Sustain_D2_v1_1.wav"
          Duplicate="0" Normalized="1" NormalizedPeak="30.095" SampleStartMod="50000"
          LoopEnabled="1" LoopEnd="258217" LoopStart="100000" LoopXFade="15000"
          UpperVelocityXFade="40" Volume="3" MonolithOffset="7847936" MonolithLength="339968"
          SampleRate="44100"/>
  <sample Root="50" LoKey="49" HiKey="50" LoVel="11" HiVel="92" RRGroup="1"
          FileName="{PROJECT_FOLDER}OldTrombone/Sustain/Trombone_Sustain_D2_v3_1.wav"
          Duplicate="0" Normalized="1" NormalizedPeak="20.7114" SampleStartMod="50000"
          LoopEnabled="1" LoopEnd="400000" LoopStart="100000" LoopXFade="15000"
          LowerVelocityXFade="40" UpperVelocityXFade="40" Volume="3" MonolithOffset="8187904"
          MonolithLength="528384" SampleRate="44100"/>
  <sample Root="50" LoKey="49" HiKey="50" LoVel="53" HiVel="125" RRGroup="1"
          FileName="{PROJECT_FOLDER}OldTrombone/Sustain/Trombone_Sustain_D2_v4_1.wav"
          Duplicate="0" Normalized="1" NormalizedPeak="1.97929" SampleStartMod="50000"
          LoopEnabled="1" LoopEnd="147666" LoopStart="78455" LoopXFade="15000"
          LowerVelocityXFade="40" UpperVelocityXFade="32" Volume="3" MonolithOffset="8716288"
          MonolithLength="192512" SampleRate="44100"/>
  <sample Root="50" LoKey="49" HiKey="50" LoVel="94" HiVel="127" RRGroup="1"
          FileName="{PROJECT_FOLDER}OldTrombone/Sustain/Trombone_Sustain_D2_v5_1.wav"
          Duplicate="0" Normalized="1" NormalizedPeak="1.99494" SampleStartMod="50000"
          LoopEnabled="1" LoopEnd="146449" LoopStart="75154" LoopXFade="15000"
          LowerVelocityXFade="32" Volume="3" MonolithOffset="8908800" MonolithLength="184320"
          SampleRate="44100"/>
  <sample Root="62" LoKey="61" HiKey="62" LoVel="0" HiVel="90" RRGroup="1"
          FileName="{PROJECT_FOLDER}OldTrombone/Sustain/Trombone_Sustain_D3_v1_1.wav"
          Duplicate="0" Normalized="1" NormalizedPeak="22.3092" SampleStartMod="50000"
          LoopEnabled="1" LoopEnd="247271" LoopStart="100000" LoopXFade="15000"
          UpperVelocityXFade="40" Volume="3" MonolithOffset="9093120" MonolithLength="335872"
          SampleRate="44100"/>
  <sample Root="62" LoKey="61" HiKey="62" LoVel="48" HiVel="121" RRGroup="1"
          FileName="{PROJECT_FOLDER}OldTrombone/Sustain/Trombone_Sustain_D3_v4_1.wav"
          Duplicate="0" Normalized="1" NormalizedPeak="4.22138" SampleStartMod="50000"
          LoopEnabled="1" LoopEnd="151876" LoopStart="69962" LoopXFade="15000"
          LowerVelocityXFade="40" UpperVelocityXFade="32" Volume="3" MonolithOffset="9428992"
          MonolithLength="200704" SampleRate="44100"/>
  <sample Root="62" LoKey="61" HiKey="62" LoVel="85" HiVel="127" RRGroup="1"
          FileName="{PROJECT_FOLDER}OldTrombone/Sustain/Trombone_Sustain_D3_v5_1.wav"
          Duplicate="0" Normalized="1" NormalizedPeak="1.91194" SampleStartMod="50000"
          LoopEnabled="1" LoopEnd="118646" LoopStart="61033" LoopXFade="15000"
          LowerVelocityXFade="32" Volume="3" MonolithOffset="9629696" MonolithLength="212992"
          SampleRate="44100"/>
  <sample Root="41" LoKey="0" HiKey="41" LoVel="0" HiVel="50" RRGroup="1"
          FileName="{PROJECT_FOLDER}OldTrombone/Sustain/Trombone_Sustain_F1_v1_1.wav"
          Duplicate="0" Normalized="1" NormalizedPeak="19.6337" SampleStartMod="50000"
          LoopEnabled="1" LoopEnd="250508" LoopStart="100000" LoopXFade="15000"
          UpperVelocityXFade="40" Volume="3" MonolithOffset="9842688" MonolithLength="307200"
          SampleRate="44100"/>
  <sample Root="41" LoKey="0" HiKey="41" LoVel="11" HiVel="92" RRGroup="1"
          FileName="{PROJECT_FOLDER}OldTrombone/Sustain/Trombone_Sustain_F1_v3_1.wav"
          Duplicate="0" Normalized="1" NormalizedPeak="11.347" SampleStartMod="50000"
          LoopEnabled="1" LoopEnd="279759" LoopStart="100000" LoopXFade="15000"
          LowerVelocityXFade="40" UpperVelocityXFade="40" Volume="3" MonolithOffset="10149888"
          MonolithLength="339968" SampleRate="44100"/>
  <sample Root="41" LoKey="0" HiKey="41" LoVel="53" HiVel="125" RRGroup="1"
          FileName="{PROJECT_FOLDER}OldTrombone/Sustain/Trombone_Sustain_F1_v4_1.wav"
          Duplicate="0" Normalized="1" NormalizedPeak="2.96622" SampleStartMod="50000"
          LoopEnabled="1" LoopEnd="111202" LoopStart="48865" LoopXFade="15000"
          LowerVelocityXFade="40" UpperVelocityXFade="32" Volume="3" MonolithOffset="10489856"
          MonolithLength="184320" SampleRate="44100"/>
  <sample Root="41" LoKey="0" HiKey="41" LoVel="94" HiVel="127" RRGroup="1"
          FileName="{PROJECT_FOLDER}OldTrombone/Sustain/Trombone_Sustain_F1_v5_1.wav"
          Duplicate="0" Normalized="1" NormalizedPeak="1.28977" SampleStartMod="50000"
          LoopEnabled="1" LoopEnd="118295" LoopStart="45732" LoopXFade="15000"
          LowerVelocityXFade="32" Volume="3" MonolithOffset="10674176"
          MonolithLength="163840" SampleRate="44100"/>
  <sample Root="53" LoKey="52" HiKey="53" LoVel="0" HiVel="50" RRGroup="1"
          FileName="{PROJECT_FOLDER}OldTrombone/Sustain/Trombone_Sustain_F2_v1_1.wav"
          Duplicate="0" Normalized="1" NormalizedPeak="20.4013" SampleStartMod="50000"
          LoopEnabled="1" LoopEnd="221444" LoopStart="100000" LoopXFade="15000"
          UpperVelocityXFade="40" Volume="3" MonolithOffset="10838016"
          MonolithLength="303104" SampleRate="44100"/>
  <sample Root="53" LoKey="52" HiKey="53" LoVel="11" HiVel="92" RRGroup="1"
          FileName="{PROJECT_FOLDER}OldTrombone/Sustain/Trombone_Sustain_F2_v3_1.wav"
          Duplicate="0" Normalized="1" NormalizedPeak="9.47657" SampleStartMod="50000"
          LoopEnabled="1" LoopEnd="400000" LoopStart="100000" LoopXFade="15000"
          LowerVelocityXFade="40" UpperVelocityXFade="40" Volume="3" MonolithOffset="11141120"
          MonolithLength="458752" SampleRate="44100"/>
  <sample Root="53" LoKey="52" HiKey="53" LoVel="53" HiVel="125" RRGroup="1"
          FileName="{PROJECT_FOLDER}OldTrombone/Sustain/Trombone_Sustain_F2_v4_1.wav"
          Duplicate="0" Normalized="1" NormalizedPeak="2.38749" SampleStartMod="50000"
          LoopEnabled="1" LoopEnd="157625" LoopStart="95733" LoopXFade="15000"
          LowerVelocityXFade="40" UpperVelocityXFade="32" Volume="3" MonolithOffset="11599872"
          MonolithLength="245760" SampleRate="44100"/>
  <sample Root="53" LoKey="52" HiKey="53" LoVel="94" HiVel="127" RRGroup="1"
          FileName="{PROJECT_FOLDER}OldTrombone/Sustain/Trombone_Sustain_F2_v5_1.wav"
          Duplicate="0" Normalized="1" NormalizedPeak="1.18981" SampleStartMod="50000"
          LoopEnabled="1" LoopEnd="162296" LoopStart="79025" LoopXFade="15000"
          LowerVelocityXFade="32" Volume="3" MonolithOffset="11845632"
          MonolithLength="262144" SampleRate="44100"/>
  <sample Root="65" LoKey="64" HiKey="127" LoVel="0" HiVel="50" RRGroup="1"
          FileName="{PROJECT_FOLDER}OldTrombone/Sustain/Trombone_Sustain_F3_v1_1.wav"
          Duplicate="0" Normalized="1" NormalizedPeak="12.8202" SampleStartMod="50000"
          LoopEnabled="1" LoopEnd="397312" LoopStart="100000" LoopXFade="15000"
          UpperVelocityXFade="40" Volume="3" MonolithOffset="12107776"
          MonolithLength="397312" SampleRate="44100"/>
  <sample Root="65" LoKey="64" HiKey="127" LoVel="11" HiVel="92" RRGroup="1"
          FileName="{PROJECT_FOLDER}OldTrombone/Sustain/Trombone_Sustain_F3_v3_1.wav"
          Duplicate="0" Normalized="1" NormalizedPeak="8.34574" SampleStartMod="50000"
          LoopEnabled="1" LoopEnd="400000" LoopStart="100000" LoopXFade="15000"
          LowerVelocityXFade="40" UpperVelocityXFade="40" Volume="3" MonolithOffset="12505088"
          MonolithLength="479232" SampleRate="44100"/>
  <sample Root="65" LoKey="64" HiKey="127" LoVel="53" HiVel="125" RRGroup="1"
          FileName="{PROJECT_FOLDER}OldTrombone/Sustain/Trombone_Sustain_F3_v4_1.wav"
          Duplicate="0" Normalized="1" NormalizedPeak="4.19112" SampleStartMod="50000"
          LoopEnabled="1" LoopEnd="150734" LoopStart="64126" LoopXFade="15000"
          LowerVelocityXFade="40" UpperVelocityXFade="32" Volume="3" MonolithOffset="12984320"
          MonolithLength="204800" SampleRate="44100"/>
  <sample Root="65" LoKey="64" HiKey="127" LoVel="94" HiVel="127" RRGroup="1"
          FileName="{PROJECT_FOLDER}OldTrombone/Sustain/Trombone_Sustain_F3_v5_1.wav"
          Duplicate="0" Normalized="1" NormalizedPeak="2.2762" SampleStartMod="50000"
          LoopEnabled="1" LoopEnd="155696" LoopStart="82859" LoopXFade="15000"
          LowerVelocityXFade="32" Volume="3" MonolithOffset="13189120"
          MonolithLength="196608" SampleRate="44100"/>
  <sample Root="43" LoKey="42" HiKey="43" LoVel="0" HiVel="50" RRGroup="1"
          FileName="{PROJECT_FOLDER}OldTrombone/Sustain/Trombone_Sustain_G1_v1_1.wav"
          Duplicate="0" Normalized="1" NormalizedPeak="24.1669" SampleStartMod="50000"
          LoopEnabled="1" LoopEnd="222912" LoopStart="100000" LoopXFade="15000"
          UpperVelocityXFade="40" Volume="3" MonolithOffset="13385728"
          MonolithLength="294912" SampleRate="44100"/>
  <sample Root="43" LoKey="42" HiKey="43" LoVel="11" HiVel="92" RRGroup="1"
          FileName="{PROJECT_FOLDER}OldTrombone/Sustain/Trombone_Sustain_G1_v3_1.wav"
          Duplicate="0" Normalized="1" NormalizedPeak="11.8221" SampleStartMod="50000"
          LoopEnabled="1" LoopEnd="239565" LoopStart="100000" LoopXFade="15000"
          LowerVelocityXFade="40" UpperVelocityXFade="40" Volume="3" MonolithOffset="13680640"
          MonolithLength="335872" SampleRate="44100"/>
  <sample Root="43" LoKey="42" HiKey="43" LoVel="53" HiVel="125" RRGroup="1"
          FileName="{PROJECT_FOLDER}OldTrombone/Sustain/Trombone_Sustain_G1_v4_1.wav"
          Duplicate="0" Normalized="1" NormalizedPeak="4.87367" SampleStartMod="50000"
          LoopEnabled="1" LoopEnd="137307" LoopStart="58846" LoopXFade="15000"
          LowerVelocityXFade="40" UpperVelocityXFade="32" Volume="3" MonolithOffset="14016512"
          MonolithLength="208896" SampleRate="44100"/>
  <sample Root="43" LoKey="42" HiKey="43" LoVel="94" HiVel="127" RRGroup="1"
          FileName="{PROJECT_FOLDER}OldTrombone/Sustain/Trombone_Sustain_G1_v5_1.wav"
          Duplicate="0" Normalized="1" NormalizedPeak="1.11534" SampleStartMod="50000"
          LoopEnabled="1" LoopEnd="103185" LoopStart="47830" LoopXFade="15000"
          LowerVelocityXFade="32" Volume="3" MonolithOffset="14225408"
          MonolithLength="143360" SampleRate="44100"/>
  <sample Root="55" LoKey="54" HiKey="55" LoVel="0" HiVel="92" RRGroup="1"
          FileName="{PROJECT_FOLDER}OldTrombone/Sustain/Trombone_Sustain_G2_v3_1.wav"
          Duplicate="0" Normalized="1" NormalizedPeak="9.04955" SampleStartMod="50000"
          LoopEnabled="1" LoopEnd="400000" LoopStart="100000" LoopXFade="15000"
          LowerVelocityXFade="0" UpperVelocityXFade="40" Volume="3" MonolithOffset="14368768"
          MonolithLength="499712" SampleRate="44100"/>
  <sample Root="55" LoKey="54" HiKey="55" LoVel="53" HiVel="125" RRGroup="1"
          FileName="{PROJECT_FOLDER}OldTrombone/Sustain/Trombone_Sustain_G2_v4_1.wav"
          Duplicate="0" Normalized="1" NormalizedPeak="2.45595" SampleStartMod="50000"
          LoopEnabled="1" LoopEnd="153818" LoopStart="80009" LoopXFade="15000"
          LowerVelocityXFade="40" UpperVelocityXFade="32" Volume="3" MonolithOffset="14868480"
          MonolithLength="237568" SampleRate="44100"/>
  <sample Root="55" LoKey="54" HiKey="55" LoVel="94" HiVel="127" RRGroup="1"
          FileName="{PROJECT_FOLDER}OldTrombone/Sustain/Trombone_Sustain_G2_v5_1.wav"
          Duplicate="0" Normalized="1" NormalizedPeak="1.46775" SampleStartMod="50000"
          LoopEnabled="1" LoopEnd="157629" LoopStart="72981" LoopXFade="15000"
          LowerVelocityXFade="32" Volume="3" MonolithOffset="15106048"
          MonolithLength="217088" SampleRate="44100"/>
</samplemap>
